genesis4/__init__.py
genesis4/driver.py
genesis4/input.py
genesis4/lattice.py
genesis4/util.py
genesis4-0.0.2.dist-info/licenses/LICENSE
genesis4-0.0.2.dist-info/METADATA
genesis4-0.0.2.dist-info/WHEEL
genesis4-0.0.2.dist-info/top_level.txt
genesis4-0.0.2.dist-info/RECORD
