Metadata-Version: 2.4
Name: genesis4
Version: 0.0.2
Summary: A warpper for Genesis4.
Author-email: Dait <dyj24@mails.tsinghua.edu.cn>
License-Expression: MIT
Classifier: Programming Language :: Python :: 3
Classifier: Operating System :: OS Independent
Requires-Python: >=3.9
License-File: LICENSE
Dynamic: license-file
